dosuby/__init__.py
dosuby/cli.py
dosuby/manage.py
dosuby/version.py
dosuby/infrastructure/__init__.py
dosuby/infrastructure/libs/__init__.py
dosuby/infrastructure/libs/loader.py
dosuby/infrastructure/libs/CrtSearch/__init__.py
dosuby/infrastructure/libs/CrtSearch/crt_search.py
dosuby/infrastructure/libs/Search_Engines_Scraper/__init__.py
dosuby/infrastructure/libs/Search_Engines_Scraper/search_engines/__init__.py
dosuby/infrastructure/libs/Search_Engines_Scraper/search_engines/config.py
dosuby/infrastructure/libs/Search_Engines_Scraper/search_engines/engine.py
dosuby/infrastructure/libs/Search_Engines_Scraper/search_engines/http_client.py
dosuby/infrastructure/libs/Search_Engines_Scraper/search_engines/multiple_search_engines.py
dosuby/infrastructure/libs/Search_Engines_Scraper/search_engines/output.py
dosuby/infrastructure/libs/Search_Engines_Scraper/search_engines/results.py
dosuby/infrastructure/libs/Search_Engines_Scraper/search_engines/utils.py
dosuby/infrastructure/libs/Search_Engines_Scraper/search_engines/engines/__init__.py
dosuby/infrastructure/libs/Search_Engines_Scraper/search_engines/engines/aol.py
dosuby/infrastructure/libs/Search_Engines_Scraper/search_engines/engines/ask.py
dosuby/infrastructure/libs/Search_Engines_Scraper/search_engines/engines/bing.py
dosuby/infrastructure/libs/Search_Engines_Scraper/search_engines/engines/brave.py
dosuby/infrastructure/libs/Search_Engines_Scraper/search_engines/engines/dogpile.py
dosuby/infrastructure/libs/Search_Engines_Scraper/search_engines/engines/duckduckgo.py
dosuby/infrastructure/libs/Search_Engines_Scraper/search_engines/engines/google.py
dosuby/infrastructure/libs/Search_Engines_Scraper/search_engines/engines/metager.py
dosuby/infrastructure/libs/Search_Engines_Scraper/search_engines/engines/mojeek.py
dosuby/infrastructure/libs/Search_Engines_Scraper/search_engines/engines/qwant.py
dosuby/infrastructure/libs/Search_Engines_Scraper/search_engines/engines/startpage.py
dosuby-1.6.7.dist-info/licenses/LICENSE
dosuby-1.6.7.dist-info/METADATA
dosuby-1.6.7.dist-info/WHEEL
dosuby-1.6.7.dist-info/entry_points.txt
dosuby-1.6.7.dist-info/top_level.txt
dosuby-1.6.7.dist-info/RECORD
